CVPubSubs-0.3.3.dist-info/METADATA
CVPubSubs-0.3.3.dist-info/RECORD
CVPubSubs-0.3.3.dist-info/WHEEL
CVPubSubs-0.3.3.dist-info/top_level.txt
cvpubsubs/__init__.py
cvpubsubs/listen_default.py
cvpubsubs/webcam_pub/__init__.py
cvpubsubs/webcam_pub/camctrl.py
cvpubsubs/webcam_pub/frame_handler.py
cvpubsubs/webcam_pub/get_cam_ids.py
cvpubsubs/webcam_pub/np_cam.py
cvpubsubs/webcam_pub/pub_cam.py
cvpubsubs/window_sub/__init__.py
cvpubsubs/window_sub/cv_window_sub.py
cvpubsubs/window_sub/winctrl.py
tests/__init__.py
tests/test_pub_cam.py
tests/test_sub_win.py
