Metadata-Version: 2.1
Name: CVPubSubs
Version: 0.3.3
Summary: UNKNOWN
Home-page: https://github.com/SimLeek/CV_PubSubs
Author: SimLeek
Author-email: josh.miklos@gmail.com
Maintainer: SimLeek
Maintainer-email: josh.miklos@gmail.com
License: MIT/Apache-2.0
Keywords: opencv,camera
Platform: UNKNOWN
Classifier: Development Status :: 4 - Beta
Classifier: Intended Audience :: Developers
Classifier: License :: OSI Approved :: MIT License
Classifier: License :: OSI Approved :: Apache Software License
Classifier: Natural Language :: English
Classifier: Operating System :: OS Independent
Classifier: Programming Language :: Python :: 2.7
Classifier: Programming Language :: Python :: 3.5
Classifier: Programming Language :: Python :: 3.6
Classifier: Programming Language :: Python :: Implementation :: CPython
Classifier: Programming Language :: Python :: Implementation :: PyPy
Requires-Dist: numpy
Requires-Dist: opencv-python
Requires-Dist: localpubsub (==0.0.1)
